{
  "version": 1,
  "deny": [
    {
      "id": "unsupported_jvm",
      "description": "Skip older JVMs",
      "os": null,
      "cmds": [
        "**/java-1.5*/**/java",
        "**/java-1.6*/**/java",
        "**/java-6*/**/java",
        "**/java-7/**/java"
      ],
      "args": [],
      "envars": null
    },
    {
      "id": "java8_version",
      "description": "Skip java -version command",
      "os": null,
      "cmds": [
        "**/java"
      ],
      "args": [
        {
          "args": [
            "-version"
          ],
          "position": 1
        }
      ],
      "envars": null
    },
    {
      "id": "java_version",
      "description": "Skip java --version command",
      "os": null,
      "cmds": [
        "**/java"
      ],
      "args": [
        {
          "args": [
            "--version"
          ],
          "position": 1
        }
      ],
      "envars": null
    },
    {
      "id": "apache_activemq_artemis",
      "description": "Skip Apache ActiveMQ Artemis",
      "os": null,
      "cmds": [
        "**/java"
      ],
      "args": [
        {
          "args": [
            "org.apache.activemq.artemis.boot.Artemis"
          ],
          "position": null
        }
      ],
      "envars": null
    },
    {
      "id": "apache_cassandra",
      "description": "Skip Apache Cassandra",
      "os": null,
      "cmds": [
        "**/java"
      ],
      "args": [
        {
          "args": [
            "org.apache.cassandra.service.CassandraDaemon"
          ],
          "position": null
        }
      ],
      "envars": null
    },
    {
      "id": "apache_cassandra_debugcql",
      "description": "Skip Apache Cassandra debug-cql",
      "os": null,
      "cmds": [
        "**/java"
      ],
      "args": [
        {
          "args": [
            "org.apache.cassandra.transport.Client"
          ],
          "position": null
        }
      ],
      "envars": null
    },
    {
      "id": "apache_cassandra_nodetool",
      "description": "Skip Apache Cassandra nodetool",
      "os": null,
      "cmds": [
        "**/java"
      ],
      "args": [
        {
          "args": [
            "org.apache.cassandra.tools.NodeTool"
          ],
          "position": null
        }
      ],
      "envars": null
    },
    {
      "id": "apache_cassandra_sstableloader",
      "description": "Skip Apache Cassandra sstableloader",
      "os": null,
      "cmds": [
        "**/java"
      ],
      "args": [
        {
          "args": [
            "org.apache.cassandra.tools.BulkLoader"
          ],
          "position": null
        }
      ],
      "envars": null
    },
    {
      "id": "apache_cassandra_sstablescrub",
      "description": "Skip Apache Cassandra stablescrub",
      "os": null,
      "cmds": [
        "**/java"
      ],
      "args": [
        {
          "args": [
            "org.apache.cassandra.tools.StandaloneScrubber"
          ],
          "position": null
        }
      ],
      "envars": null
    },
    {
      "id": "apache_cassandra_sstableupgrade",
      "description": "Skip Apache Cassandra sstableupgrade",
      "os": null,
      "cmds": [
        "**/java"
      ],
      "args": [
        {
          "args": [
            "org.apache.cassandra.tools.StandaloneUpgrader"
          ],
          "position": null
        }
      ],
      "envars": null
    },
    {
      "id": "apache_cassandra_sstableutil",
      "description": "Skip Apache Cassandra sstableutil",
      "os": null,
      "cmds": [
        "**/java"
      ],
      "args": [
        {
          "args": [
            "org.apache.cassandra.tools.StandaloneSSTableUtil"
          ],
          "position": null
        }
      ],
      "envars": null
    },
    {
      "id": "apache_cassandra_sstableverify",
      "description": "Skip Apache Cassandra sstableverify",
      "os": null,
      "cmds": [
        "**/java"
      ],
      "args": [
        {
          "args": [
            "org.apache.cassandra.tools.StandaloneVerifier"
          ],
          "position": null
        }
      ],
      "envars": null
    },
    {
      "id": "oracle_dbca",
      "description": "Skip Oracle Database Configuration Assistant",
      "os": null,
      "cmds": [
        "**/java"
      ],
      "args": [
        {
          "args": [
            "oracle.assistants.dbca.driver.DBConfigurator"
          ],
          "position": null
        }
      ],
      "envars": null
    },
    {
      "id": "oracle_dbua",
      "description": "Skip Oracle Database Upgrade Assistant",
      "os": null,
      "cmds": [
        "**/java"
      ],
      "args": [
        {
          "args": [
            "oracle.assistants.dbua.driver.StartDBUA"
          ],
          "position": null
        }
      ],
      "envars": null
    },
    {
      "id": "oracle_emca",
      "description": "Skip Oracle Enterprise Manager Configuration Assistant",
      "os": null,
      "cmds": [
        "**/java"
      ],
      "args": [
        {
          "args": [
            "oracle.sysman.assistants.emca.sdkimpl.EMConfigAssistant"
          ],
          "position": null
        }
      ],
      "envars": null
    },
    {
      "id": "oracle_invctl",
      "description": "Skip Oracle Inventory Control",
      "os": null,
      "cmds": [
        "**/java"
      ],
      "args": [
        {
          "args": [
            "oracle.install.common.endpoints.cli.CliExecutor"
          ],
          "position": null
        }
      ],
      "envars": null
    },
    {
      "id": "oracle_netca",
      "description": "Skip Oracle Net Configuration Assistant",
      "os": null,
      "cmds": [
        "**/java"
      ],
      "args": [
        {
          "args": [
            "oracle.net.ca.NetCA"
          ],
          "position": null
        }
      ],
      "envars": null
    },
    {
      "id": "oracle_rconfig",
      "description": "Skip Oracle RAC Converter",
      "os": null,
      "cmds": [
        "**/java"
      ],
      "args": [
        {
          "args": [
            "oracle.sysman.assistants.rconfig.RConfig"
          ],
          "position": null
        }
      ],
      "envars": null
    },
    {
      "id": "oracle_roohctl",
      "description": "Skip Oracle Read-Only Oracle Home Control",
      "os": null,
      "cmds": [
        "**/java"
      ],
      "args": [
        {
          "args": [
            "oracle.assistants.roohctl.RoohCtl"
          ],
          "position": null
        }
      ],
      "envars": null
    },
    {
      "id": "oracle_srvctl",
      "description": "Skip Oracle Server Control Utility",
      "os": null,
      "cmds": [
        "**/java"
      ],
      "args": [
        {
          "args": [
            "oracle.ops.opsctl.OPSCTLDriver"
          ],
          "position": null
        }
      ],
      "envars": null
    },
    {
      "id": "oracle_diagsetup",
      "description": "Skip Oracle Setup Diagnostic Tool",
      "os": null,
      "cmds": [
        "**/java"
      ],
      "args": [
        {
          "args": [
            "oracle.diagfw.adr.diagsetup.DiagSetup"
          ],
          "position": null
        }
      ],
      "envars": null
    },
    {
      "id": "oracle_ldifmigrator",
      "description": "Skip Oracle LDIF Migration Tool",
      "os": null,
      "cmds": [
        "**/java"
      ],
      "args": [
        {
          "args": [
            "oracle.ldap.util.LDIFMigration"
          ],
          "position": null
        }
      ],
      "envars": null
    },
    {
      "id": "oracle_trcasst",
      "description": "Skip Oracle Trace Assistant",
      "os": null,
      "cmds": [
        "**/java"
      ],
      "args": [
        {
          "args": [
            "oracle.net.trcasst.Jtrcasst"
          ],
          "position": null
        }
      ],
      "envars": null
    },
    {
      "id": "oracle_trcsess",
      "description": "Skip Oracle Session Tracer",
      "os": null,
      "cmds": [
        "**/java"
      ],
      "args": [
        {
          "args": [
            "oracle.ss.tools.trcsess.TrcSess"
          ],
          "position": null
        }
      ],
      "envars": null
    },
    {
      "id": "apache_lucene8_luke",
      "description": "Skip Lucene 8 Luke",
      "os": null,
      "cmds": [
        "**/java"
      ],
      "args": [
        {
          "args": [
            "org.apache.lucene.luke.app.desktop.LukeMain"
          ],
          "position": null
        }
      ],
      "envars": null
    },
    {
      "id": "apache_lucene9_luke",
      "description": "Skip Apache Netbeans",
      "os": null,
      "cmds": [
        "**/java"
      ],
      "args": [
        {
          "args": [
            "org.apache.lucene.luke"
          ],
          "position": null
        }
      ],
      "envars": null
    },
    {
      "id": "apache_netbeans",
      "description": "Skip Apache Netbeans",
      "os": null,
      "cmds": [
        "**/java"
      ],
      "args": [
        {
          "args": [
            "org.netbeans.Main"
          ],
          "position": null
        }
      ],
      "envars": null
    },
    {
      "id": "apache_solr8_start",
      "description": "Skip Apache Solr 8 start command using System Properties",
      "os": null,
      "cmds": [
        "**/java"
      ],
      "args": [
        {
          "args": [
            "-Dsolr.solr.home=*"
          ],
          "position": null
        }
      ],
      "envars": null
    },
    {
      "id": "apache_solr8_stop",
      "description": "Skip Apache Solr 8 stop using path to jar",
      "os": null,
      "cmds": [
        "**/java"
      ],
      "args": [
        {
          "args": [
            "*solr/server/start.jar"
          ],
          "position": null
        }
      ],
      "envars": null
    },
    {
      "id": "apache_solr8_tools",
      "description": "Skip Apache Solr 8 CLI tools",
      "os": null,
      "cmds": [
        "**/java"
      ],
      "args": [
        {
          "args": [
            "org.apache.solr.util.SolrCLI"
          ],
          "position": null
        }
      ],
      "envars": null
    },
    {
      "id": "datadog_jmxfetch",
      "description": "Skip DataDog JMXFetch",
      "os": null,
      "cmds": [
        "**/java"
      ],
      "args": [
        {
          "args": [
            "org.datadog.jmxfetch.App"
          ],
          "position": null
        }
      ],
      "envars": null
    },
    {
      "id": "open_liberty_utility_main",
      "description": "Skip UtilityMain that expected single jar in classpath",
      "os": null,
      "cmds": [
        "**/java"
      ],
      "args": [
        {
          "args": [
            "com.ibm.ws.kernel.boot.cmdline.UtilityMain"
          ],
          "position": null
        }
      ],
      "envars": null
    },
    {
      "id": "ibm_ikeycmd",
      "description": "Skip IBM ikeycmd utility",
      "os": null,
      "cmds": [
        "**/java"
      ],
      "args": [
        {
          "args": [
            "com.ibm.gsk.ikeyman.ikeycmd"
          ],
          "position": null
        }
      ],
      "envars": null
    },
    {
      "id": "ibm_ikeyman",
      "description": "Skip IBM Ikeyman utility",
      "os": null,
      "cmds": [
        "**/java"
      ],
      "args": [
        {
          "args": [
            "com.ibm.gsk.ikeyman.Ikeyman"
          ],
          "position": null
        }
      ],
      "envars": null
    },
    {
      "id": "elasticsearch7",
      "description": "Skip Elastic Search 7+ commands",
      "os": null,
      "cmds": [
        "**/java"
      ],
      "args": [
        {
          "args": [
            "-Des.path.home=*"
          ],
          "position": null
        }
      ],
      "envars": null
    },
    {
      "id": "intellij_idea",
      "description": "Skip Jetbrains IntelliJ IDEA",
      "os": null,
      "cmds": [
        "**/java"
      ],
      "args": [
        {
          "args": [
            "com.intellij.idea.Main"
          ],
          "position": null
        }
      ],
      "envars": null
    },
    {
      "id": "apache_solr9",
      "description": "Skip Apache Solr 9",
      "os": null,
      "cmds": [
        "**/java"
      ],
      "args": [],
      "envars": {
        "SOLR_PORT": null
      }
    }
  ],
  "native_deps": {
    "glibc": [
      {
        "arch": "x86",
        "supported": true
      },
      {
        "arch": "x64",
        "supported": true
      },
      {
        "arch": "arm64",
        "supported": true
      }
    ],
    "musl": [
      {
        "arch": "x86",
        "supported": true
      },
      {
        "arch": "x64",
        "supported": true
      },
      {
        "arch": "arm64",
        "supported": true
      }
    ]
  }
}
